Workbook

Sheet Cover
A1: Super Micro Computer, Inc. — Quality of Earnings
A2: Buy-side diligence (public-information Phase 1)
A4: Prepared as | B4: Illustrative buy-side QoE for a hypothetical take-private of SMCI.
A5: Basis of preparation | B5: Public SEC filings only. No trial balance, no management access, no cut-off testing. Phase 1 / pre-LOI scope.
A6: Periods | B6: FY2023 / FY2024 / FY2025 (fiscal years end June 30).
A7: Currency / units | B7: USD, in thousands (matches the 10-K).
A9: Colour convention
A10: Blue | B10: Hard-coded input — a sourced or assumed number.
A11: Black | B11: Formula — a computed cell.
A12: Green | B12: Link to another sheet.
A13: Amber tab | B13: Assumptions — the only non-sourced numbers in the model.
A15: Source documents | B15: SMCI FY2023/FY2024/FY2025 10-K; FY2022/FY2025/FY2026 DEF 14A; 8-K 2024-10-30 (Item 4.01, EY resignation).
A16: Control note | B16: Balance sheet balances and income-statement subtotals are re-derived on every run; the model raises on any missing sourced figure.

Sheet Assumptions
A1: Assumptions — non-sourced inputs (amber)
A2: Everything here is a CHOICE, not a filing figure. Kept few and explicit.
A4: ID | B4: Assumption | C4: Low | D4: High | E4: Basis
A5: A-1 | B5: Illustrative EV / EBITDA multiple (x) | C5: 12 | D5: 18 | E5: Sensitivity range only; not a valuation opinion.
A6: A-2 | B6: Pro forma compliant finance-function cost ($000s/yr) | C6: 15000 | D6: 40000 | E6: Benchmarked to peer proxy audit-fee + G&A headcount; ADJ-003.

Sheet EBITDA Bridge
A1: EBITDA Bridge — three-tier walk (FY2025)
A2: $ in thousands. Green cells link to Source Data; black cells are formulas.
A4: ID | B4: Line | C4: Amount | D4: Treatment | E4: Tickmark (source)
B5: GAAP EBITDA (Operating income + D&A) | C5: ='Source Data'!C242+'Source Data'!C170 | D5: subtotal | E5: IS: Operating income; CF: D&A
A6: ADJ-001 | B6: + Stock-based compensation (contested) | C6: ='Source Data'!C184 | D6: BOTH | E6: CF: Stock-based compensation
A7: ADJ-002 | B7: + Incremental audit fees vs FY22 baseline | C7: ='Source Data'!C304-'Source Data'!C307 | D7: ACCEPT | E7: DEF 14A: Principal Accountant Fees
B8: =Management-basis EBITDA (SBC added back) | C8: =C5+C6
B9: =Diligence Adj. EBITDA — SBC added back | C9: =C5+C6+C7
B10: =Diligence Adj. EBITDA — SBC as real cost | C10: =C5+C7
B12: SBC decision swing (EBITDA): | C12: =C6
B13: SBC swing at Assumptions A-1 low multiple (EV): | C13: =C6*Assumptions!C5
B15: Not booked (shown as exposures on Adjustment Schedule): ADJ-003 finance-function cost, ADJ-004 related-party pricing, ADJ-005 ramp-cost reversal.

Sheet Adjustment Schedule
A1: Adjustment Schedule — rationale AND counterargument
A2: Every adjustment carries the seller's pushback. Nothing is booked without it.
A4: ID | B4: Adjustment | C4: Tier | D4: Treatment | E4: Mkt practice | F4: Rationale | G4: Counterargument (seller)
A5: ADJ-001 | B5: Stock-based compensation | C5: management | D5: BOTH | E5: contested | F5: Non-cash and excluded from SMCI's own non-GAAP measures; comparable-company multiples are typically struck on an SBC-excluded basis, so excluding it keeps metric and multiple consistent. | G5: SBC is real compensation. Strip it out and you must replace it with cash to retain engineers, so it is a recurring economic cost; it also dilutes the buyer. Present BOTH bases and show the dilution separately — do not treat it as a free add-back.
A6: ADJ-002 | B6: Incremental audit fees (accounting-crisis, vs FY2022 pre-crisis baseline) | C6: diligence | D6: ACCEPT | E6: standard | F6: Discrete, non-recurring incremental audit cost from the crisis, sourced hard from the proxy "Principal Accountant Fees and Services" tables. A FLOOR on crisis cost, not the total. | G6: Seller: obviously non-recurring, the investigation is over. Buy-side: accept the incremental AUDIT fee only; the far larger forensic/legal/consulting costs sit unquantifiably in G&A, and a permanently-compliant SMCI carries structurally higher ongoing audit fees than pre-crisis.
A7: ADJ-003 | B7: Pro forma cost of a compliant finance function | C7: diligence | D7: SENSITIVITY | E7: standard | F7: Remediating five material weaknesses is not one-time: permanent incremental accounting/internal -audit headcount, a real SOX program, systems, and higher ongoing audit fees. A properly controlled SMCI has a structurally higher G&A run-rate than it has ever had -> a NEGATIVE adjustment. This is the clearest "think like a buyer" signal in the model. | G7: Seller: remediation is temporary project cost, not run-rate; scale absorbs it (G&A already falling as a % of revenue). Buy-side answer: size it as a range benchmarked to peers and run it as a sensitivity; make the compliant-cost build a Day-1 integration line item.
A8: ADJ-004 | B8: Related-party pricing normalization (arm's-length COGS) | C8: diligence | D8: SENSITIVITY | E8: standard_to_test | F8: 3.3%-6.6% of COGS runs through CEO-family-affiliated entities (Ablecom, Compuware). If they supply below market, reported COGS is understated and EBITDA is subsidized by the founder's family — a subsidy the buyer may not inherit. | G8: Seller: long-standing, fully disclosed, audit-committee-reviewed, priced at market. Buy-side: quantify exposure + per-100bps sensitivity now; make an arm's-length benchmarking study a condition precedent. Booking a specific number without the study is aggressive.
A9: ADJ-005 | B9: Reverse management "non-recurring ramp cost" add-backs | C9: management | D9: REJECT | E9: standard_buyside | F9: In a hardware business that has "ramped" for several consecutive years, expedite freight and ramp inefficiency are the cost of operating, not an anomaly. Test: will this cost exist for the buyer next year? If yes, it is not non-recurring. | G9: Seller: genuinely one-time ramp/expedite costs; margins normalize at scale. Buy-side: reject or accept only a discrete, invoice-substantiated slice. Cannot be quantified from public data — flagged as a scoped diligence request, not a booked number.

Sheet NWC
A1: Net Working Capital — peg schedule
A2: $ in thousands. Cash-free/debt-free; excludes cash, debt, income taxes.
A4: Component | B4: FY2023 | C4: FY2024 | D4: FY2025 | E4: Tickmark
A5: + Accounts receivable, net | B5: ='Source Data'!C14 | C5: ='Source Data'!C15 | D5: ='Source Data'!C16 | E5: Balance sheet / Note 6
A6: + Inventories, net | B6: ='Source Data'!C53 | C6: ='Source Data'!C54 | D6: ='Source Data'!C55 | E6: Balance sheet / Note 6
A7: + Prepaid & other current assets | B7: ='Source Data'!C75 | C7: ='Source Data'!C76 | D7: ='Source Data'!C77 | E7: Balance sheet / Note 6
A8: - Accounts payable | B8: =-'Source Data'!C5 | C8: =-'Source Data'!C6 | D8: =-'Source Data'!C7 | E8: Balance sheet / Note 6
A9: - Accrued liabilities | B9: =-'Source Data'!C23 | C9: =-'Source Data'!C24 | D9: =-'Source Data'!C25 | E9: Balance sheet / Note 6
A10: - Deferred revenue, current | B10: =-'Source Data'!C44 | C10: =-'Source Data'!C45 | D10: =-'Source Data'!C46 | E10: Balance sheet / Note 6
A11: =Net working capital | B11: =SUM(B5:B10) | C11: =SUM(C5:C10) | D11: =SUM(D5:D10)
A12: NWC as % of revenue | B12: =B11/'Source Data'!C271 | C12: =C11/'Source Data'!C272 | D12: =D11/'Source Data'!C273
A14: Peg note: recommend pegging NWC as a % of LTM revenue, not a trailing dollar average — a dollar peg transfers value to the seller in a working-capital-hungry growth business.

Sheet CCC & Diagnostics
A1: Cash conversion & earnings quality
A2: Turnover on average balances where a prior period exists.
A4: Metric | B4: FY2023 | C4: FY2024 | D4: FY2025 | E4: Read
A5: DIO (days) | B5: 90.340479 | C5: 81.575355 | D5: 84.1744 | E5: Inventory days
A6: DSO (days) | B6: 58.835628 | C6: 47.30858 | D6: 41.042263 | E6: Receivable days
A7: DPO (days) | B7: 48.54803 | C7: 31.75172 | D7: 25.722406 | E7: Payable days — falling = suppliers want cash
A8: CCC (days) | B8: 100.62808 | C8: 97.132215 | D8: 99.494258 | E8: DIO+DSO-DPO
A9: NWC ($000s) | B9: 1663604 | C9: 5337087 | D9: 4915392 | E9: Absolute NWC
A10: NWC / revenue | B10: 0.23353804 | C10: 0.35606095 | D10: 0.22371121 | E10: The operating metric
A11: Accruals ratio | C11: 0.5390247 | D11: -0.051220991 | E11: (NI-CFO)/avg assets — Sloan
A13: Beneish M-score (screen; read components)
A14: Year | B14: DSRI | C14: GMI | D14: AQI | E14: SGI | F14: DEPI | G14: SGAI | H14: TATA | I14: LVGI | J14: M | K14: Flag
A15: FY2024 | B15: 1.1329216 | C15: 1.3096461 | D15: 0.87560977 | E15: 2.1042028 | F15: 1.4829472 | G15: 0.85718024 | H15: 0.37030368 | I15: 0.96840057 | J15: 0.56356411 | K15: FLAG
A16: FY2025 | B16: 0.54926555 | C16: 1.2435479 | D16: 1.769838 | E16: 1.4658532 | F16: 0.74053828 | G16: 0.95235192 | H16: -0.043561943 | I16: 1.2268526 | J16: -2.3391765 | K16: ok
A18: Note: FY2024 flags, driven partly by SGI (sales doubled — benign growth). The components that matter are DSRI>1, GMI>1, DEPI>1; corroborated by the 54% accruals ratio.

Sheet Source Data
A1: Source Data — every figure, with provenance
A2: $ in thousands. FILED = from filing; ASSUMPTION = chosen input; NOT_DISCLOSED = filing is silent (a finding).
A4: Line item | B4: Period | C4: Value ($000s) | D4: Source | E4: Reference | F4: Provenance
A5: Accounts payable | B5: FY2023 | C5: 776831 | D5: 10-K | E5: XBRL AccountsPayableCurrent | 0001375365-23-000036 | F5: FILED
A6: Accounts payable | B6: FY2024 | C6: 1472381 | D6: 10-K | E6: XBRL AccountsPayableCurrent | 0001375365-25-000004 | F6: FILED
A7: Accounts payable | B7: FY2025 | C7: 1281977 | D7: 10-K | E7: XBRL AccountsPayableCurrent | 0001375365-25-000027 | F7: FILED
A8: Accounts payable | B8: Q/E 2024-09-30 | C8: 1682968 | D8: 10-Q | E8: XBRL AccountsPayableCurrent | 0001375365-25-000005 | F8: FILED
A9: Accounts payable | B9: Q/E 2024-12-31 | C9: 549323 | D9: 10-Q | E9: XBRL AccountsPayableCurrent | 0001375365-25-000006 | F9: FILED
A10: Accounts payable | B10: Q/E 2025-03-31 | C10: 643050 | D10: 10-Q | E10: XBRL AccountsPayableCurrent | 0001375365-25-000014 | F10: FILED
A11: Accounts payable | B11: Q/E 2025-09-30 | C11: 1279667 | D11: 10-Q | E11: XBRL AccountsPayableCurrent | 0001375365-25-000030 | F11: FILED
A12: Accounts payable | B12: Q/E 2025-12-31 | C12: 13753207 | D12: 10-Q | E12: XBRL AccountsPayableCurrent | 0001375365-26-000007 | F12: FILED
A13: Accounts payable | B13: Q/E 2026-03-31 | C13: 3686991 | D13: 10-Q | E13: XBRL AccountsPayableCurrent | 0001375365-26-000014 | F13: FILED
A14: Accounts receivable, net | B14: FY2023 | C14: 1148259 | D14: 10-K | E14: XBRL AccountsReceivableNetCurrent | 0001375365-23-000036 | F14: FILED
A15: Accounts receivable, net | B15: FY2024 | C15: 2737331 | D15: 10-K | E15: XBRL AccountsReceivableNetCurrent | 0001375365-25-000004 | F15: FILED
A16: Accounts receivable, net | B16: FY2025 | C16: 2203942 | D16: 10-K | E16: XBRL AccountsReceivableNetCurrent | 0001375365-25-000027 | F16: FILED
... A61: Inventories, net | B61: Q/E 2026-03-31 | C61: 11103376 | D61: 10-Q | E61: XBRL InventoryNet | 0001375365-26-000014 | F61: FILED
A62: Inventory - E&O reserve | B62: FY2025 | D62: SMCI FY2025 10-K | E62: Note 6 - NOT SEPARATELY DISCLOSED (inventory stated net; disclosure gap) | F62: NOT_DISCLOSED
A63: Inventory - finished goods | B63: FY2024 | C63: 3312768 | D63: SMCI FY2025 10-K | E63: Note 6 Balance Sheet Components, Inventories | F63: FILED
A64: Inventory - finished goods | B64: FY2025 | C64: 3465352 | D64: SMCI FY2025 10-K | E64: Note 6 Balance Sheet Components, Inventories | F64: FILED
A65: Inventory - purchased parts and raw materials | B65: FY2024 | C65: 569268 | D65: SMCI FY2025 10-K | E65: Note 6 Balance Sheet Components, Inventories | F65: FILED
A66: Inventory - purchased parts and raw materials | B66: FY2025 | C66: 540410 | D66: SMCI FY2025 10-K | E66: Note 6 Balance Sheet Components, Inventories | F66: FILED
A67: Inventory - work in process | B67: FY2024 | C67: 450993 | D67: SMCI FY2025 10-K | E67: Note 6 Balance Sheet Components, Inventories | F67: FILED
A68: Inventory - work in process | B68: FY2025 | C68: 674613 | D68: SMCI FY2025 10-K | E68: Note 6 Balance Sheet Components, Inventories | F68: FILED
A69: Lines of credit and current portion of term loans | B69: FY2024 | C69: 402346 | D69: SMCI FY2025 10-K | E69: Consolidated Balance Sheets | F69: FILED
A70: Lines of credit and current portion of term loans | B70: FY2025 | C70: 75060 | D70: SMCI FY2025 10-K | E70: Consolidated Balance Sheets | F70: FILED
A71: Long-term debt noncurrent (legacy term loans) | B71: FY2023 | C71: 120179 | D71: SMCI FY2024 10-K | E71: Consolidated Balance Sheets (XBRL LongTermDebtNoncurrent) | F71: FILED
A72: Long-term debt, noncurrent | B72: FY2023 | C72: 120179 | D72: 10-K | E72: XBRL LongTermDebtNoncurrent | 0001375365-23-000036 | F72: FILED
A73: Non-controlling interest | B73: FY2024 | C73: 164 | D73: SMCI FY2025 10-K | E73: Consolidated Balance Sheets (XBRL MinorityInterest) | F73: FILED
A74: Non-controlling interest | B74: FY2025 | C74: 178 | D74: SMCI FY2025 10-K | E74: Consolidated Balance Sheets (XBRL MinorityInterest) | F74: FILED
... A307: Audit fees (Deloitte) | B307: FY2022 | C307: 4488 | D307: SMCI DEF 14A (FY2022 proxy) | E307: Principal Accountant Fees and Services | F307: FILED
